slpcollections/__init__.py
slpcollections/list.py
slpcollections-0.0.1a1.dist-info/LICENSE
slpcollections-0.0.1a1.dist-info/METADATA
slpcollections-0.0.1a1.dist-info/WHEEL
slpcollections-0.0.1a1.dist-info/top_level.txt
slpcollections-0.0.1a1.dist-info/RECORD
