Metadata-Version: 2.1
Name: slpcollections
Version: 0.0.1a1
Summary: Data Structure Collections
Home-page: https://github.com/GaoangLiu/slpcollections
Author: SLP
Author-email: byteleap@gmail.com
License: UNKNOWN
Platform: UNKNOWN
Classifier: Programming Language :: Python :: 3
Classifier: License :: OSI Approved :: MIT License
Classifier: Operating System :: OS Independent
